odoo/addons/auditlog/README.rst
odoo/addons/auditlog/__init__.py
odoo/addons/auditlog/__manifest__.py
odoo/addons/auditlog/data/ir_cron.xml
odoo/addons/auditlog/i18n/am.po
odoo/addons/auditlog/i18n/ar.po
odoo/addons/auditlog/i18n/auditlog.pot
odoo/addons/auditlog/i18n/bg.po
odoo/addons/auditlog/i18n/bs.po
odoo/addons/auditlog/i18n/ca.po
odoo/addons/auditlog/i18n/cs.po
odoo/addons/auditlog/i18n/cs_CZ.po
odoo/addons/auditlog/i18n/da.po
odoo/addons/auditlog/i18n/de.po
odoo/addons/auditlog/i18n/el_GR.po
odoo/addons/auditlog/i18n/en_GB.po
odoo/addons/auditlog/i18n/es.po
odoo/addons/auditlog/i18n/es_AR.po
odoo/addons/auditlog/i18n/es_CL.po
odoo/addons/auditlog/i18n/es_CO.po
odoo/addons/auditlog/i18n/es_CR.po
odoo/addons/auditlog/i18n/es_DO.po
odoo/addons/auditlog/i18n/es_EC.po
odoo/addons/auditlog/i18n/es_ES.po
odoo/addons/auditlog/i18n/es_MX.po
odoo/addons/auditlog/i18n/es_PE.po
odoo/addons/auditlog/i18n/es_PY.po
odoo/addons/auditlog/i18n/es_VE.po
odoo/addons/auditlog/i18n/et.po
odoo/addons/auditlog/i18n/eu.po
odoo/addons/auditlog/i18n/fa.po
odoo/addons/auditlog/i18n/fi.po
odoo/addons/auditlog/i18n/fr.po
odoo/addons/auditlog/i18n/fr_CA.po
odoo/addons/auditlog/i18n/fr_CH.po
odoo/addons/auditlog/i18n/fr_FR.po
odoo/addons/auditlog/i18n/gl.po
odoo/addons/auditlog/i18n/gl_ES.po
odoo/addons/auditlog/i18n/he.po
odoo/addons/auditlog/i18n/hr.po
odoo/addons/auditlog/i18n/hr_HR.po
odoo/addons/auditlog/i18n/hu.po
odoo/addons/auditlog/i18n/id.po
odoo/addons/auditlog/i18n/it.po
odoo/addons/auditlog/i18n/ja.po
odoo/addons/auditlog/i18n/ko.po
odoo/addons/auditlog/i18n/lt.po
odoo/addons/auditlog/i18n/lt_LT.po
odoo/addons/auditlog/i18n/lv.po
odoo/addons/auditlog/i18n/mk.po
odoo/addons/auditlog/i18n/mn.po
odoo/addons/auditlog/i18n/nb.po
odoo/addons/auditlog/i18n/nb_NO.po
odoo/addons/auditlog/i18n/nl.po
odoo/addons/auditlog/i18n/nl_BE.po
odoo/addons/auditlog/i18n/nl_NL.po
odoo/addons/auditlog/i18n/pl.po
odoo/addons/auditlog/i18n/pt.po
odoo/addons/auditlog/i18n/pt_BR.po
odoo13_addon_auditlog-13.0.1.2.0.dist-info/METADATA
odoo13_addon_auditlog-13.0.1.2.0.dist-info/WHEEL
odoo13_addon_auditlog-13.0.1.2.0.dist-info/top_level.txt
odoo13_addon_auditlog-13.0.1.2.0.dist-info/RECORD
